{
  "contacts": [
    {
      "id": "D6BNdWnHI",
      "name": "Brad Gibson",
      "company": "YouTube",
      "email": "brad@gmail.com",
      "title": "Mr",
      "jobTitle": "Frontend Developer",
      "mobile": "9876546787",
      "photo": "https://encrypted-tbn0.gstatic.com/images?q=tbn:ANd9GcT0g8R5VmgqDqpRCwQfw2Y9V-DM-iXS59R9hQ&usqp=CAU",
      "groupId": "3"
    },
    {
      "id": "TVobxeKbI",
      "name": "Glenda Kim",
      "company": "Friend",
      "email": "glenda@gmail.com",
      "title": "Mr",
      "jobTitle": "Frontend Developer",
      "mobile": "8880009991",
      "photo": "https://www.kindpng.com/picc/m/163-1636340_user-avatar-icon-avatar-transparent-user-icon-png.png",
      "groupId": "2"
    },
    {
      "id": "UyEDV5Yds",
      "name": "Vladeen Min",
      "company": "Service",
      "email": "vladeen@gmail.com",
      "title": "Mr",
      "jobTitle": "Frontend Developer",
      "mobile": "9876546787",
      "photo": "https://png.pngtree.com/png-clipart/20190922/original/pngtree-business-male-user-avatar-vector-png-image_4774078.jpg",
      "groupId": "4"
    },
    {
      "title": "Mr",
      "name": "Timothy Mbachu",
      "mobile": "08133992971",
      "email": "follow.timothy@gmail.com",
      "jobTitle": "Frontend Developer",
      "company": "Self",
      "groupId": "Social",
      "id": "hHzUjzs"
    },
    {
      "title": "Mrs",
      "name": "Timothy Mbachu",
      "mobile": "08133992971",
      "email": "follow.timothy@gmail.com",
      "jobTitle": "Frontend Developer",
      "company": "Me",
      "groupId": "Community",
      "photo": "https://picsum.photos/200",
      "id": "dM7iaEc"
    }
  ],
  "groups": [
    {
      "id": "1",
      "name": "Colleague"
    },
    {
      "id": "2",
      "name": "Friend"
    },
    {
      "id": "3",
      "name": "Family"
    },
    {
      "id": "4",
      "name": "Service"
    },
    {
      "id": "5",
      "name": "Community"
    },
    {
      "id": "6",
      "name": "Social"
    }
  ]
}